Metadata-Version: 2.1
Name: oneNeuron-pypi-sureshs96
Version: 0.0.2
Summary: its an implimentation of Perceptron
Home-page: https://github.com/sureshs96/oneNeuron_pypi
Author: sureshs96
Author-email: sunny.c17hawke@gmail.com
Project-URL: Bug Tracker, https://github.com/sureshs96/oneNeuron_pypi/issues
Classifier: Programming Language :: Python :: 3
Classifier: License :: OSI Approved :: MIT License
Classifier: Operating System :: OS Independent
Requires-Python: >=3.7
License-File: LICENSE
Requires-Dist: numpy
Requires-Dist: tqdm
